nlp_id/__init__.py
nlp_id/data/dataset_postag.txt
nlp_id/data/lemma_dict.json
nlp_id/data/non_clitics.txt
nlp_id/data/root-word.txt
nlp_id/data/stopword.txt
nlp_id/lemmatizer.py
nlp_id/postag.py
nlp_id/stopword.py
nlp_id/tokenizer.py
nlp_id-0.1.19.0.dist-info/LICENSE
nlp_id-0.1.19.0.dist-info/METADATA
nlp_id-0.1.19.0.dist-info/WHEEL
nlp_id-0.1.19.0.dist-info/RECORD
