Metadata-Version: 2.1
Name: nlp-id
Version: 0.1.19.0
Summary: kumparan's NLP Services
Home-page: https://github.com/kumparan/NLP-ID
License: MIT
Author: Zavli Juwantara
Author-email: zavli.juwantara@kumparan.com
Maintainer: Frandy Eddy
Maintainer-email: eddy.frandy@gmail.com
Requires-Python: >=3.10,<3.12
Classifier: License :: OSI Approved :: MIT License
Classifier: Programming Language :: Python :: 3
Classifier: Programming Language :: Python :: 3.10
Classifier: Programming Language :: Python :: 3.11
Requires-Dist: huggingface-hub (==0.31.1)
Requires-Dist: nltk (==3.9.1)
Requires-Dist: numpy (==2.0.2)
Requires-Dist: scikit-learn (==1.6.1)
Requires-Dist: scipy (==1.15.3)
Requires-Dist: wget (==3.2)
Project-URL: Repository, https://github.com/kumparan/NLP-ID
